cloudflare.py
crypto.py
gbackup.py
gbak-2.80.data/scripts/gbak
gbak-2.80.dist-info/METADATA
gbak-2.80.dist-info/WHEEL
gbak-2.80.dist-info/top_level.txt
gbak-2.80.dist-info/RECORD
