Metadata-Version: 2.1
Name: gbak
Version: 2.80
Summary: A Des of gbak
Home-page: https://github.com/vtandroid/gbackup
Author: Thanh Hoa
Author-email: getmoneykhmt3@gmail.com
Classifier: Programming Language :: Python :: 3
Classifier: License :: OSI Approved :: MIT License
Classifier: Operating System :: OS Independent
Requires-Dist: youtube-dl
Requires-Dist: google-api-python-client==1.7.11
Requires-Dist: click
Requires-Dist: google-auth-httplib2>=0.0.3
Requires-Dist: google-auth-oauthlib>=0.4.1
Requires-Dist: httplib2==0.15.0
Requires-Dist: cryptography
Requires-Dist: python-slugify
Requires-Dist: boto3
